PyZoo/__init__.py
PyZoo/pyZoo.py
PyZoo/builderCheck/__init__.py
PyZoo/builderCheck/builderCheck.py
PyZoo/builderCheck/extraArgument.py
PyZoo/builderCheck/exceptions/__init__.py
PyZoo/formatter/__init__.py
PyZoo/formatter/format.py
PyZoo/formatter/loaderTemplate.py
PyZoo/formatter/templates/DefaultMessages.json
PyZoo/formatter/templates/DefaultVariables.json
PyZoo/formatter/templates/__init__.py
PyZoo/typesPyZoo/__init__.py
PyZoo/typesPyZoo/base.py
PyZoo/typesPyZoo/caller.py
PyZoo/typesPyZoo/complexTypes.py
PyZoo/typesPyZoo/numberTypes.py
PyZoo/typesPyZoo/textTypes.py
PyZoo/typesPyZoo/exceptions/__init__.py
PyZoo/typesPyZoo/exceptions/constructorException.py
PyZoo/typesPyZoo/exceptions/typeException.py
PyZoo/validators/__init__.py
PyZoo/validators/argumentRules.py
PyZoo/validators/ruleValidator.py
PyZoo/validators/validator.py
PyZoo/validators/exceptions/__init__.py
PyZoo/validators/exceptions/argumentException.py
PyZoo/validators/exceptions/objectException.py
PyZoo/validators/utils/__init__.py
PyZoo/validators/utils/listSecure.py
PyZoo-0.1.0.data/data/PyZoo/DefaultMessages.json
PyZoo-0.1.0.data/data/PyZoo/DefaultVariables.json
PyZoo-0.1.0.dist-info/METADATA
PyZoo-0.1.0.dist-info/WHEEL
PyZoo-0.1.0.dist-info/top_level.txt
PyZoo-0.1.0.dist-info/RECORD
