Metadata-Version: 2.1
Name: PyZoo
Version: 0.1.0
Summary: Python library for data validation
Home-page: UNKNOWN
Author: Alan Franzin
Author-email: alan.franzin2011@gmail.com
License: MIT
Platform: UNKNOWN
Classifier: Development Status :: 1 - Planning
Classifier: Environment :: Web Environment
Classifier: Natural Language :: Portuguese (Brazilian)
Classifier: Operating System :: Unix
Classifier: Programming Language :: Python :: 3
Classifier: Topic :: Software Development :: Libraries :: Python Modules
Requires-Python: >=3
